ContainerAll/DsAll_Package.py
ContainerAll/__init__.py
DataVisualization/Univariate.py
DataVisualization/__init__.py
PreprocessData/__init__.py
PreprocessData/anova.py
PreprocessData/gridsearch.py
PreprocessData/model.py
PreprocessData/preprocessing.py
metrics/__init__.py
metrics/check_overfit.py
replacer/__init__.py
replacer/mean_mode_replacer.py
DataVipLibraries-0.0.1.dist-info/LICENSE.txt
DataVipLibraries-0.0.1.dist-info/METADATA
DataVipLibraries-0.0.1.dist-info/WHEEL
DataVipLibraries-0.0.1.dist-info/top_level.txt
DataVipLibraries-0.0.1.dist-info/RECORD
